CoT/__init__.py
CoT/types.py
CoT/utils.py
CoT/models/__init__.py
CoT/models/core.py
CoT/xml/__init__.py
pycot-3.0.0.dist-info/licenses/LICENSE
pycot-3.0.0.dist-info/METADATA
pycot-3.0.0.dist-info/WHEEL
pycot-3.0.0.dist-info/top_level.txt
pycot-3.0.0.dist-info/RECORD
